<?xml version="1.0" encoding="utf-8" ?>
<dwsync>
<file name="gal_adv.png" server="virtualquimia.50webs.com" local="130558473259065991" remote="130559487600000000" />
<file name="gal_arn.png" server="virtualquimia.50webs.com" local="130558467694537718" remote="130559487600000000" />
<file name="gal_dor.png" server="virtualquimia.50webs.com" local="130558457565038344" remote="130559487600000000" />
<file name="gal_han.png" server="virtualquimia.50webs.com" local="130558446664954894" remote="130559487600000000" />
<file name="gal_inc.png" server="virtualquimia.50webs.com" local="130558431940402698" remote="130559488200000000" />
<file name="gal_kim.png" server="virtualquimia.50webs.com" local="130558430552643323" remote="130559488200000000" />
<file name="gal_rob.png" server="virtualquimia.50webs.com" local="130558453790672462" remote="130559488200000000" />
<file name="gal_upu.png" server="virtualquimia.50webs.com" local="130558474226071300" remote="130559488200000000" />
</dwsync>